PyDeduplines-0.6.1.dist-info/METADATA
PyDeduplines-0.6.1.dist-info/WHEEL
pydeduplines/pydeduplines.pyi
pydeduplines/__init__.py
pydeduplines/pydeduplines.cpython-310-x86_64-linux-gnu.so
PyDeduplines-0.6.1.dist-info/RECORD
