Metadata-Version: 2.1
Name: PyDeduplines
Version: 0.6.1
Summary: Python library for a duplicate lines removal written in Rust
Keywords: unique,lines,rust,pyo3
Home-Page: https://github.com/intsights/PyDeduplines
Author: Gal Ben David <gal@intsights.com>
Author-email: Gal Ben David <gal@intsights.com>
License: MIT
Project-URL: Source Code, https://github.com/intsights/PyDeduplines
